pyovo/__init__.py
pyovo/client.py
pyovo-0.0.9.dist-info/LICENSE
pyovo-0.0.9.dist-info/METADATA
pyovo-0.0.9.dist-info/WHEEL
pyovo-0.0.9.dist-info/entry_points.txt
pyovo-0.0.9.dist-info/top_level.txt
pyovo-0.0.9.dist-info/RECORD
