Metadata-Version: 2.1
Name: pyovo
Version: 0.0.9
Summary: a set of physical simulation devtoys
Author-email: VeriTas-arch <veritas-k@qq.com>
Project-URL: Homepage, https://github.com/Ancient-Gadget-Laboratory/pyovo
Project-URL: Issues, https://github.com/Ancient-Gadget-Laboratory/pyovo/issues
Classifier: Programming Language :: Python :: 3
Classifier: License :: OSI Approved :: MIT License
Classifier: Operating System :: OS Independent
Requires-Python: >=3.12
License-File: LICENSE
Provides-Extra: dev
Requires-Dist: black; extra == "dev"
Requires-Dist: numpy; extra == "dev"
Requires-Dist: taichi; extra == "dev"
